colab_preamble.py
colab_preamble-0.1.3.dist-info/LICENSE
colab_preamble-0.1.3.dist-info/METADATA
colab_preamble-0.1.3.dist-info/WHEEL
colab_preamble-0.1.3.dist-info/top_level.txt
colab_preamble-0.1.3.dist-info/RECORD
