Metadata-Version: 2.1
Name: colab-preamble
Version: 0.1.3
Summary: Prepare google colabpratory by one line of command
Home-page: https://github.com/kota7/colab-preamble
Author: Kota Mori
Author-email: kmori05@gmail.com
License-File: LICENSE
Requires-Dist: google-colab
Requires-Dist: another-bigquery-magic
